.gitignore
MANIFEST.in
README.md
setup.py
mpbn_sim/__init__.py
mpbn_sim/cli.py
mpbn_sim/impl.py
mpbn_sim.egg-info/PKG-INFO
mpbn_sim.egg-info/SOURCES.txt
mpbn_sim.egg-info/dependency_links.txt
mpbn_sim.egg-info/entry_points.txt
mpbn_sim.egg-info/requires.txt
mpbn_sim.egg-info/top_level.txt