Metadata-Version: 2.1
Name: mpbn-sim
Version: 0.1
Summary: Simulation of Most Permissive Boolean networks
Home-page: https://github.com/bnediction/mpbn-sim
Author: Loïc Paulevé
Author-email: loic.pauleve@labri.fr
Classifier: Intended Audience :: Science/Research
Classifier: Topic :: Scientific/Engineering
Classifier: Topic :: Scientific/Engineering :: Artificial Intelligence
Classifier: Topic :: Scientific/Engineering :: Bio-Informatics
